secretsantasolver/SecretSantaSolver.py
secretsantasolver/__init__.py
secretsantasolver-0.1.0.dist-info/WHEEL
secretsantasolver-0.1.0.dist-info/METADATA
secretsantasolver-0.1.0.dist-info/RECORD
