Metadata-Version: 2.1
Name: secretsantasolver
Version: 0.1.0
Summary: 
Author: Martin Helm
Author-email: martin@bio-ai.org
Requires-Python: >=3.7,<4.0
Classifier: Programming Language :: Python :: 3
Classifier: Programming Language :: Python :: 3.7
Classifier: Programming Language :: Python :: 3.8
Classifier: Programming Language :: Python :: 3.9
Classifier: Programming Language :: Python :: 3.10
